magpie_ai/TEST_CONFIG_CLIENT.py
magpie_ai/__init__.py
magpie_ai/client.py
magpie_ai/config.py
magpie_ai/content_moderation.py
magpie_ai/context.py
magpie_ai/monitor.py
magpie_ai/pii.py
magpie_ai/pricing.py
magpie_ai/prompt.py
magpie_ai/py.typed
magpie_ai/token_extraction.py
magpie_ai/validation.py
magpie_ai-0.2.8.dist-info/METADATA
magpie_ai-0.2.8.dist-info/WHEEL
magpie_ai-0.2.8.dist-info/top_level.txt
magpie_ai-0.2.8.dist-info/RECORD
